.DS_Store
py_ms_sql/__init__.py
py_ms_sql/py_ms_sql.py
py_ms_sql-0.2.2.dist-info/LICENSE
py_ms_sql-0.2.2.dist-info/METADATA
py_ms_sql-0.2.2.dist-info/WHEEL
py_ms_sql-0.2.2.dist-info/top_level.txt
py_ms_sql-0.2.2.dist-info/RECORD
