Metadata-Version: 2.1
Name: py-ms-sql
Version: 0.2.2
Summary: A small utility package that makes connecting to Microsoft SQL easier
Home-page: https://github.com/TheBookReeder/py-ms-sql
Author: Timothy Reeder
Author-email: timothy.reeder23@gmail.com
License: UNKNOWN
Keywords: sql sqlserver
Platform: UNKNOWN
Classifier: Development Status :: 3 - Alpha
Classifier: Programming Language :: Python :: 3
Classifier: License :: OSI Approved :: MIT License
Classifier: Operating System :: OS Independent
Requires-Python: >=3.6
Requires-Dist: sqlalchemy
Requires-Dist: pyodbc
Requires-Dist: pandas
